LICENSE
MANIFEST.in
README.rst
setup.py
gapic_google_cloud_spanner_admin_instance_v1.egg-info/PKG-INFO
gapic_google_cloud_spanner_admin_instance_v1.egg-info/SOURCES.txt
gapic_google_cloud_spanner_admin_instance_v1.egg-info/dependency_links.txt
gapic_google_cloud_spanner_admin_instance_v1.egg-info/namespace_packages.txt
gapic_google_cloud_spanner_admin_instance_v1.egg-info/requires.txt
gapic_google_cloud_spanner_admin_instance_v1.egg-info/top_level.txt
google/__init__.py
google/cloud/__init__.py
google/cloud/gapic/__init__.py
google/cloud/gapic/spanner_admin_instance/__init__.py
google/cloud/gapic/spanner_admin_instance/v1/__init__.py
google/cloud/gapic/spanner_admin_instance/v1/enums.py
google/cloud/gapic/spanner_admin_instance/v1/instance_admin_client.py
google/cloud/gapic/spanner_admin_instance/v1/instance_admin_client_config.json